freiner/__init__.py
freiner/errors.py
freiner/limits.py
freiner/py.typed
freiner/types.py
freiner/util.py
freiner/storage/__init__.py
freiner/storage/memcached.py
freiner/storage/memory.py
freiner/storage/redis.py
freiner/storage/redis_cluster.py
freiner/storage/redis_sentinel.py
freiner/strategies/__init__.py
freiner/strategies/fixed_window.py
freiner/strategies/fixed_window_elastic.py
freiner/strategies/moving_window.py
freiner-3.1.0.dist-info/LICENSE.txt
freiner-3.1.0.dist-info/METADATA
freiner-3.1.0.dist-info/WHEEL
freiner-3.1.0.dist-info/top_level.txt
freiner-3.1.0.dist-info/RECORD
