Metadata-Version: 2.1
Name: freiner
Version: 3.1.0
Summary: Generic rate limiting solution for python applications, supporting various strategies and storage backends (redis and memcached).
Home-page: https://github.com/djmattyg007/freiner
Author: Matthew Gamble
Author-email: git@matthewgamble.net
License: MIT
Project-URL: Documentation, https://freiner.readthedocs.io/
Project-URL: Source, https://github.com/djmattyg007/freiner
Project-URL: Issues, https://github.com/djmattyg007/freiner/issues
Platform: UNKNOWN
Classifier: Development Status :: 5 - Production/Stable
Classifier: Intended Audience :: Developers
Classifier: License :: OSI Approved :: MIT License
Classifier: Operating System :: OS Independent
Classifier: Programming Language :: Python :: 3.8
Classifier: Programming Language :: Python :: 3.9
Classifier: Programming Language :: Python :: 3.10
Requires-Python: >=3.8
License-File: LICENSE.txt
Provides-Extra: build
Requires-Dist: build ; extra == 'build'
Requires-Dist: twine ; extra == 'build'
Provides-Extra: dev
Requires-Dist: wheel ; extra == 'dev'
Requires-Dist: invoke ; extra == 'dev'
Requires-Dist: sphinx (<5.0.0,>=4.4.0) ; extra == 'dev'
Requires-Dist: sphinx-rtd-theme (==1.0.0) ; extra == 'dev'
Requires-Dist: readthedocs-sphinx-search (==0.1.1) ; extra == 'dev'
Requires-Dist: pymemcache ; extra == 'dev'
Requires-Dist: redis ; extra == 'dev'
Requires-Dist: redis-py-cluster ; extra == 'dev'
Requires-Dist: bandit ; extra == 'dev'
Requires-Dist: black ; extra == 'dev'
Requires-Dist: check-manifest ; extra == 'dev'
Requires-Dist: darglint ; extra == 'dev'
Requires-Dist: flake8 ; extra == 'dev'
Requires-Dist: flake8-annotations-complexity ; extra == 'dev'
Requires-Dist: flake8-black ; extra == 'dev'
Requires-Dist: flake8-breakpoint ; extra == 'dev'
Requires-Dist: flake8-bugbear ; extra == 'dev'
Requires-Dist: flake8-builtins ; extra == 'dev'
Requires-Dist: flake8-comprehensions ; extra == 'dev'
Requires-Dist: flake8-eradicate ; extra == 'dev'
Requires-Dist: flake8-expression-complexity ; extra == 'dev'
Requires-Dist: flake8-isort ; extra == 'dev'
Requires-Dist: flake8-pytest-style ; extra == 'dev'
Requires-Dist: flake8-requirements ; extra == 'dev'
Requires-Dist: isort ; extra == 'dev'
Requires-Dist: pep8-naming ; extra == 'dev'
Requires-Dist: mypy ; extra == 'dev'
Requires-Dist: types-freezegun ; extra == 'dev'
Requires-Dist: types-redis ; extra == 'dev'
Requires-Dist: coverage[toml] ; extra == 'dev'
Requires-Dist: freezegun ; extra == 'dev'
Requires-Dist: pytest ; extra == 'dev'
Requires-Dist: pytest-cov ; extra == 'dev'
Provides-Extra: docs
Requires-Dist: sphinx (<5.0.0,>=4.4.0) ; extra == 'docs'
Requires-Dist: sphinx-rtd-theme (==1.0.0) ; extra == 'docs'
Requires-Dist: readthedocs-sphinx-search (==0.1.1) ; extra == 'docs'
Requires-Dist: pymemcache ; extra == 'docs'
Requires-Dist: redis ; extra == 'docs'
Requires-Dist: redis-py-cluster ; extra == 'docs'
Provides-Extra: lint
Requires-Dist: bandit ; extra == 'lint'
Requires-Dist: black ; extra == 'lint'
Requires-Dist: check-manifest ; extra == 'lint'
Requires-Dist: darglint ; extra == 'lint'
Requires-Dist: flake8 ; extra == 'lint'
Requires-Dist: flake8-annotations-complexity ; extra == 'lint'
Requires-Dist: flake8-black ; extra == 'lint'
Requires-Dist: flake8-breakpoint ; extra == 'lint'
Requires-Dist: flake8-bugbear ; extra == 'lint'
Requires-Dist: flake8-builtins ; extra == 'lint'
Requires-Dist: flake8-comprehensions ; extra == 'lint'
Requires-Dist: flake8-eradicate ; extra == 'lint'
Requires-Dist: flake8-expression-complexity ; extra == 'lint'
Requires-Dist: flake8-isort ; extra == 'lint'
Requires-Dist: flake8-pytest-style ; extra == 'lint'
Requires-Dist: flake8-requirements ; extra == 'lint'
Requires-Dist: isort ; extra == 'lint'
Requires-Dist: pep8-naming ; extra == 'lint'
Provides-Extra: test
Requires-Dist: coverage[toml] ; extra == 'test'
Requires-Dist: freezegun ; extra == 'test'
Requires-Dist: pymemcache ; extra == 'test'
Requires-Dist: pytest ; extra == 'test'
Requires-Dist: pytest-cov ; extra == 'test'
Requires-Dist: redis ; extra == 'test'
Provides-Extra: typecheck
Requires-Dist: mypy ; extra == 'typecheck'
Requires-Dist: types-freezegun ; extra == 'typecheck'
Requires-Dist: types-redis ; extra == 'typecheck'
